logdecomp/__init__.py
logdecomp/functions.py
logdecomp/lu.cp38-win32.pyd
logdecomp/test_functions.py
logdecomp-0.2.dist-info/LICENSE
logdecomp-0.2.dist-info/METADATA
logdecomp-0.2.dist-info/WHEEL
logdecomp-0.2.dist-info/top_level.txt
logdecomp-0.2.dist-info/RECORD
